{
    "datetime": "2019-05-05T15:25:13.724686+0000",
    "domain": [
        128,
        128,
        80
    ],
    "runinfo": {
        "backend": "mc",
        "clustername": "daint",
        "compiler": "/opt/cray/pe/craype/2.5.15/bin/CC 7.3.0",
        "datetime": "2019-05-05T14:57:14.000000+0000",
        "grid": "structured",
        "hostname": "daint105",
        "name": "gridtools",
        "precision": "float",
        "version": "7f39a6f2b1ad7729f49629bb12e945aab2765690"
    },
    "times": [
        {
            "measurements": [
                0.00243708,
                0.00243356,
                0.00243626,
                0.00244137,
                0.00240105,
                0.00249294,
                0.00244286,
                0.00244752,
                0.00243327,
                0.00244939
            ],
            "stencil": "copy"
        },
        {
            "measurements": [
                0.00487865,
                0.00485032,
                0.00481145,
                0.00483776,
                0.00490506,
                0.00489881,
                0.00484845,
                0.004919,
                0.00481048,
                0.00489715
            ],
            "stencil": "horizontal diffusion"
        },
        {
            "measurements": [
                0.00509634,
                0.00498113,
                0.00499806,
                0.00496248,
                0.00499205,
                0.00520808,
                0.00518984,
                0.00515071,
                0.00500958,
                0.0051228
            ],
            "stencil": "horizontal diffusion fused"
        },
        {
            "measurements": [
                0.00601411,
                0.00586087,
                0.00589437,
                0.00592698,
                0.00598089,
                0.00590929,
                0.00594542,
                0.00593738,
                0.00598061,
                0.005855
            ],
            "stencil": "simple horizontal diffusion"
        },
        {
            "measurements": [
                0.0171812,
                0.0172627,
                0.017108,
                0.0172229,
                0.0171871,
                0.0172461,
                0.01715,
                0.0170452,
                0.0170333,
                0.0171459
            ],
            "stencil": "vertical advection"
        },
        {
            "measurements": [
                0.0315505,
                0.0318448,
                0.0316817,
                0.0317808,
                0.0316975,
                0.0315569,
                0.0318379,
                0.0310103,
                0.031579,
                0.0318574
            ],
            "stencil": "advection pd bott"
        }
    ],
    "version": 0.5
}