{
    "config": {
        "clustername": "kesch",
        "configname": "kesch_gcc",
        "hostname": "keschln-0002"
    },
    "datetime": "2018-04-11T13:02:39.496126+0000",
    "domain": [
        128,
        128,
        80
    ],
    "runtime": {
        "backend": "cuda",
        "compiler": "/global/opt/nvidia/cudatoolkit/8.0.61/bin/nvcc",
        "datetime": "2018-04-11T12:37:02.000000+0000",
        "grid": "structured",
        "name": "gridtools",
        "precision": "double",
        "version": "3b0663ad223fb2de45d85b3abc0f6e4a6ab591f2"
    },
    "times": [
        {
            "measurements": [
                0.00143424,
                0.0014312,
                0.00142976,
                0.00143315,
                0.0014353,
                0.00143216,
                0.00143693,
                0.00143382,
                0.00143488,
                0.00144045
            ],
            "stencil": "copy"
        },
        {
            "measurements": [
                0.00378675,
                0.0037857,
                0.00376483,
                0.00375379,
                0.00375942,
                0.00378458,
                0.00375251,
                0.00379562,
                0.00378192,
                0.00378666
            ],
            "stencil": "horizontal diffusion"
        },
        {
            "measurements": [
                0.00259571,
                0.00258659,
                0.00258746,
                0.0025969,
                0.00259072,
                0.0025919,
                0.00258618,
                0.00258422,
                0.0025913,
                0.00258685
            ],
            "stencil": "horizontal diffusion fused"
        },
        {
            "measurements": [
                0.00289651,
                0.0029,
                0.00289955,
                0.00289325,
                0.00339923,
                0.00289712,
                0.00289866,
                0.00288416,
                0.00290048,
                0.00289341
            ],
            "stencil": "simple horizontal diffusion"
        },
        {
            "measurements": [
                0.00992541,
                0.00989824,
                0.0098681,
                0.0102174,
                0.00989309,
                0.0098575,
                0.00985472,
                0.00986608,
                0.00987357,
                0.00988563
            ],
            "stencil": "vertical advection"
        },
        {
            "measurements": [
                0.0192621,
                0.0192377,
                0.0192734,
                0.0192382,
                0.0192529,
                0.0195193,
                0.0192839,
                0.019632,
                0.0192445,
                0.0192442
            ],
            "stencil": "advection pd bott"
        }
    ],
    "version": 0.4
}