{
    "config": {
        "clustername": "daint",
        "configname": "daint_gcc",
        "hostname": "daint104"
    },
    "datetime": "2018-04-05T07:03:13.614387+0000",
    "domain": [
        128,
        128,
        80
    ],
    "runtime": {
        "backend": "host",
        "compiler": "/opt/gcc/5.3.0/bin/g++",
        "datetime": "2018-04-05T06:27:18.000000+0000",
        "grid": "structured",
        "name": "gridtools",
        "precision": "double",
        "version": "498eb761af0cc9ce832cfecb45d4082e67202ab6"
    },
    "times": [
        {
            "measurements": [
                0.00489594,
                0.00490419,
                0.00492623,
                0.00492443,
                0.00482536,
                0.00497837,
                0.00485168,
                0.00522635,
                0.00494872,
                0.00488475
            ],
            "stencil": "copy"
        },
        {
            "measurements": [
                0.0131252,
                0.0131807,
                0.0132084,
                0.0133276,
                0.0133241,
                0.0131409,
                0.0131385,
                0.0131754,
                0.0132277,
                0.013254
            ],
            "stencil": "horizontal diffusion"
        },
        {
            "measurements": [
                0.0198766,
                0.0199028,
                0.0197865,
                0.0198636,
                0.0199235,
                0.0197316,
                0.0198821,
                0.0198893,
                0.019827,
                0.0197776
            ],
            "stencil": "horizontal diffusion fused"
        },
        {
            "measurements": [
                0.00945989,
                0.00945381,
                0.00963904,
                0.0095593,
                0.00957281,
                0.00944943,
                0.00948434,
                0.00953599,
                0.00971537,
                0.0096374
            ],
            "stencil": "simple horizontal diffusion"
        },
        {
            "measurements": [
                0.0187707,
                0.0190513,
                0.0187817,
                0.0187656,
                0.0188844,
                0.0188864,
                0.0187353,
                0.0188131,
                0.0186902,
                0.0190729
            ],
            "stencil": "vertical advection"
        },
        {
            "measurements": [
                0.072457,
                0.0717514,
                0.0716552,
                0.071846,
                0.0713189,
                0.0716539,
                0.0715443,
                0.0716774,
                0.0714781,
                0.0713233
            ],
            "stencil": "advection pd bott"
        }
    ],
    "version": 0.4
}