{
    "datetime": "2019-09-27T08:42:09.891438+0000",
    "domain": [
        256,
        256,
        80
    ],
    "runinfo": {
        "backend": "mc",
        "clustername": "daint",
        "compiler": "/opt/cray/pe/craype/2.5.15/bin/CC 7.3.0",
        "datetime": "2019-09-26T12:02:00.000000+0000",
        "grid": "structured",
        "hostname": "daint102",
        "name": "gridtools",
        "precision": "float",
        "version": "091320b4b2a5428c2fba0f814b8c2f7ecbe9a211"
    },
    "times": [
        {
            "measurements": [
                0.0100685,
                0.00996889,
                0.00987223,
                0.00990243,
                0.0100419,
                0.00976966,
                0.009934,
                0.0098973,
                0.0100864,
                0.010017
            ],
            "stencil": "copy"
        },
        {
            "measurements": [
                0.0155368,
                0.0154425,
                0.0155382,
                0.0155232,
                0.0155802,
                0.0155388,
                0.0155444,
                0.0154752,
                0.0155489,
                0.015553
            ],
            "stencil": "horizontal diffusion"
        },
        {
            "measurements": [
                0.0160508,
                0.0157469,
                0.0158919,
                0.0159234,
                0.0158141,
                0.0158589,
                0.0158902,
                0.0160087,
                0.0160108,
                0.0157769
            ],
            "stencil": "horizontal diffusion fused"
        },
        {
            "measurements": [
                0.0347154,
                0.034757,
                0.0344805,
                0.0344649,
                0.034024,
                0.0344025,
                0.0343664,
                0.0343009,
                0.0341486,
                0.0342652
            ],
            "stencil": "simple horizontal diffusion"
        },
        {
            "measurements": [
                0.0742055,
                0.0751373,
                0.07513,
                0.0747909,
                0.0745377,
                0.0741748,
                0.0738414,
                0.0745326,
                0.074465,
                0.0741452
            ],
            "stencil": "vertical advection"
        },
        {
            "measurements": [
                0.142042,
                0.142346,
                0.142071,
                0.141892,
                0.144078,
                0.143165,
                0.142842,
                0.142126,
                0.142223,
                0.141996
            ],
            "stencil": "advection pd bott"
        },
        {
            "measurements": [
                0.032014,
                0.0327043,
                0.0325519,
                0.0321531,
                0.0324642,
                0.0326362,
                0.0320053,
                0.03286,
                0.0320486,
                0.032585
            ],
            "stencil": "layout transformation"
        },
        {
            "measurements": [
                0.00426453,
                0.00427982,
                0.00427187,
                0.00423381,
                0.00426707,
                0.00437385,
                0.00429471,
                0.00428234,
                0.00422534,
                0.00425912
            ],
            "stencil": "boundary conditions"
        }
    ],
    "version": 0.5
}