{
    "config": {
        "clustername": "daint",
        "configname": "daint_gcc",
        "hostname": "daint102"
    },
    "datetime": "2018-09-19T09:13:42.448307+0000",
    "domain": [
        256,
        256,
        80
    ],
    "runtime": {
        "backend": "cuda",
        "compiler": "/opt/nvidia/cudatoolkit9.0/9.0.103_3.7-6.0.4.1_2.1__g72b395b/bin/nvcc",
        "datetime": "2018-09-19T07:13:07.000000+0000",
        "grid": "icosahedral",
        "name": "gridtools",
        "precision": "double",
        "version": "d5bebca04ffb23e71bef3526ff42808fe7e330f8"
    },
    "times": [
        {
            "measurements": [
                0.0166182,
                0.01665,
                0.0166978,
                0.0166321,
                0.0167832,
                0.0166686,
                0.0166065,
                0.016728,
                0.0166689,
                0.0166886
            ],
            "stencil": "stencil on edges multifields"
        },
        {
            "measurements": [
                0.00496602,
                0.00497501,
                0.00494291,
                0.00505728,
                0.00507296,
                0.00506474,
                0.00507216,
                0.0049703,
                0.00496022,
                0.00496387
            ],
            "stencil": "stencil on cells"
        },
        {
            "measurements": [
                0.00745885,
                0.0072623,
                0.00741354,
                0.00727261,
                0.00741491,
                0.0074537,
                0.00723907,
                0.007236,
                0.0073951,
                0.00736973
            ],
            "stencil": "stencil on neighcell of edges"
        },
        {
            "measurements": [
                0.0143719,
                0.0145669,
                0.014179,
                0.0141662,
                0.0144997,
                0.0143346,
                0.0145944,
                0.0146825,
                0.0147475,
                0.0142492
            ],
            "stencil": "stencil manual fold"
        }
    ],
    "version": 0.4
}