{
    "datetime": "2019-05-27T10:02:53.554604+0000",
    "domain": [
        128,
        128,
        80
    ],
    "runinfo": {
        "backend": "x86",
        "clustername": "tave",
        "compiler": "/opt/gcc/7.3.0/bin/g++ 7.3.0",
        "datetime": "2019-05-27T08:07:49.000000+0000",
        "grid": "structured",
        "hostname": "tave102",
        "name": "gridtools",
        "precision": "float",
        "version": "783cd5eb16d1f1193555c301aab8bf4efc0697df"
    },
    "times": [
        {
            "measurements": [
                0.00336678,
                0.00342259,
                0.00338181,
                0.0036284,
                0.00345321,
                0.003414,
                0.00336376,
                0.00339749,
                0.00336705,
                0.00341305
            ],
            "stencil": "copy"
        },
        {
            "measurements": [
                0.0255304,
                0.0253107,
                0.0254956,
                0.0256169,
                0.0254709,
                0.0254044,
                0.025288,
                0.0253666,
                0.0254703,
                0.0254735
            ],
            "stencil": "horizontal diffusion"
        },
        {
            "measurements": [
                0.0578989,
                0.0584278,
                0.0586414,
                0.0587044,
                0.0588474,
                0.0585334,
                0.0578466,
                0.0583366,
                0.057408,
                0.0584926
            ],
            "stencil": "horizontal diffusion fused"
        },
        {
            "measurements": [
                0.0178925,
                0.0178002,
                0.0174983,
                0.018125,
                0.0178882,
                0.0179038,
                0.0184819,
                0.0175776,
                0.0180475,
                0.0180853
            ],
            "stencil": "simple horizontal diffusion"
        },
        {
            "measurements": [
                0.0935096,
                0.0937302,
                0.0930142,
                0.0932587,
                0.0934991,
                0.093548,
                0.0939092,
                0.0935061,
                0.093556,
                0.0935678
            ],
            "stencil": "vertical advection"
        },
        {
            "measurements": [
                0.0434661,
                0.0436222,
                0.0434938,
                0.0439743,
                0.0434058,
                0.0437563,
                0.0440185,
                0.0436858,
                0.0436494,
                0.0436856
            ],
            "stencil": "advection pd bott"
        },
        {
            "measurements": [
                0.00396473,
                0.0038867,
                0.0039294,
                0.00395667,
                0.00380745,
                0.00375785,
                0.00434546,
                0.0039759,
                0.00400568,
                0.00389129
            ],
            "stencil": "layout transformation"
        }
    ],
    "version": 0.5
}