{
    "config": {
        "clustername": "daint",
        "configname": "daint_gcc",
        "hostname": "daint103"
    },
    "datetime": "2018-07-13T07:00:28.695123+0000",
    "domain": [
        256,
        256,
        80
    ],
    "runtime": {
        "backend": "cuda",
        "compiler": "/opt/nvidia/cudatoolkit8.0/8.0.61_2.4.3-6.0.4.0_3.1__gb475d12/bin/nvcc",
        "datetime": "2018-07-10T11:08:20.000000+0000",
        "grid": "structured",
        "name": "gridtools",
        "precision": "double",
        "version": "a86d8c562d336077811680770007e5745ab45a7f"
    },
    "times": [
        {
            "measurements": [
                0.00166323,
                0.00166739,
                0.00165923,
                0.00166365,
                0.00166314,
                0.00166195,
                0.00165962,
                0.00166304,
                0.00166358,
                0.0016591
            ],
            "stencil": "copy"
        },
        {
            "measurements": [
                0.00457126,
                0.00455702,
                0.00455786,
                0.00455872,
                0.00455622,
                0.0055785,
                0.00456989,
                0.00456371,
                0.00457699,
                0.00457635
            ],
            "stencil": "horizontal diffusion"
        },
        {
            "measurements": [
                0.00426003,
                0.00425341,
                0.00427658,
                0.00425661,
                0.00425821,
                0.00428301,
                0.00427418,
                0.00427763,
                0.00425917,
                0.00424707
            ],
            "stencil": "horizontal diffusion fused"
        },
        {
            "measurements": [
                0.00404032,
                0.00402925,
                0.00402624,
                0.00403184,
                0.0040207,
                0.0040257,
                0.00402762,
                0.00403456,
                0.0040337,
                0.00403146
            ],
            "stencil": "simple horizontal diffusion"
        },
        {
            "measurements": [
                0.00925856,
                0.00925389,
                0.00924656,
                0.00926205,
                0.00925795,
                0.00924768,
                0.00926534,
                0.00927683,
                0.00925709,
                0.00925482
            ],
            "stencil": "vertical advection"
        },
        {
            "measurements": [
                0.02207,
                0.0220844,
                0.0220487,
                0.0220658,
                0.0220657,
                0.0220758,
                0.0220724,
                0.0220658,
                0.0220646,
                0.022058
            ],
            "stencil": "advection pd bott"
        }
    ],
    "version": 0.4
}