{
    "config": {
        "clustername": "kesch",
        "configname": "kesch_gcc",
        "hostname": "keschln-0003"
    },
    "datetime": "2019-03-25T14:08:46.353344+0000",
    "domain": [
        128,
        128,
        80
    ],
    "runtime": {
        "backend": "x86",
        "compiler": "/apps/escha/UES/jenkins/RH7.3-gnu_PE17.02/easybuild/software/gcccore/5.4.0/bin/g++",
        "datetime": "2019-03-25T12:48:58.000000+0000",
        "grid": "structured",
        "name": "gridtools",
        "precision": "double",
        "version": "fb8134dcd28b83d5df502ee35b30cb90fc753fa9"
    },
    "times": [
        {
            "measurements": [
                0.00557913,
                0.00557578,
                0.00560129,
                0.00557094,
                0.00563726,
                0.00559027,
                0.00557172,
                0.00586366,
                0.00560312,
                0.00555919
            ],
            "stencil": "copy"
        },
        {
            "measurements": [
                0.0135647,
                0.0134956,
                0.0134902,
                0.0133777,
                0.0133902,
                0.0137483,
                0.0134963,
                0.0134584,
                0.0138793,
                0.0135446
            ],
            "stencil": "horizontal diffusion"
        },
        {
            "measurements": [
                0.350354,
                0.351109,
                0.349199,
                0.350621,
                0.350263,
                0.351879,
                0.350892,
                0.351644,
                0.348374,
                0.350713
            ],
            "stencil": "horizontal diffusion fused"
        },
        {
            "measurements": [
                0.0100685,
                0.0179944,
                0.0100606,
                0.0102891,
                0.0100596,
                0.0100204,
                0.0108328,
                0.0100392,
                0.0101479,
                0.0100896
            ],
            "stencil": "simple horizontal diffusion"
        },
        {
            "measurements": [
                0.0269449,
                0.0269787,
                0.026899,
                0.0273523,
                0.0280645,
                0.0269193,
                0.0268687,
                0.0271753,
                0.0269253,
                0.0269446
            ],
            "stencil": "vertical advection"
        },
        {
            "measurements": [
                0.0810927,
                0.0812223,
                0.0814567,
                0.0808197,
                0.0814179,
                0.0807999,
                0.0811937,
                0.0810611,
                0.0814225,
                0.0805755
            ],
            "stencil": "advection pd bott"
        }
    ],
    "version": 0.4
}