{
    "config": {
        "clustername": "daint",
        "configname": "daint_gcc",
        "hostname": "daint103"
    },
    "datetime": "2018-10-12T12:23:28.848003+0000",
    "domain": [
        256,
        256,
        80
    ],
    "runtime": {
        "backend": "cuda",
        "compiler": "/opt/nvidia/cudatoolkit9.1/9.1.85_3.18-6.0.7.0_5.1__g2eb7c52/bin/nvcc",
        "datetime": "2018-10-12T12:10:37.000000+0000",
        "grid": "structured",
        "name": "gridtools",
        "precision": "float",
        "version": "0e6a9302b0b453d32fcf72109c2c3848aa48a9b9"
    },
    "times": [
        {
            "measurements": [
                0.000869856,
                0.000870496,
                0.00086944,
                0.0008696,
                0.00087024,
                0.000872864,
                0.000871232,
                0.000872032,
                0.000871008,
                0.000872096
            ],
            "stencil": "copy"
        },
        {
            "measurements": [
                0.00342118,
                0.00341485,
                0.00343075,
                0.00342403,
                0.00341859,
                0.00341552,
                0.00341456,
                0.0034224,
                0.00340739,
                0.00342378
            ],
            "stencil": "horizontal diffusion"
        },
        {
            "measurements": [
                0.00307254,
                0.00301485,
                0.00304083,
                0.00305987,
                0.00306294,
                0.00303693,
                0.00305363,
                0.0030536,
                0.00303674,
                0.00304941
            ],
            "stencil": "horizontal diffusion fused"
        },
        {
            "measurements": [
                0.00303792,
                0.00301946,
                0.0030367,
                0.00302877,
                0.00303315,
                0.00302886,
                0.00304579,
                0.00302832,
                0.00302403,
                0.00302906
            ],
            "stencil": "simple horizontal diffusion"
        },
        {
            "measurements": [
                0.00532976,
                0.00532822,
                0.00532611,
                0.00531754,
                0.00532989,
                0.00531594,
                0.00531894,
                0.00532259,
                0.00532291,
                0.00531971
            ],
            "stencil": "vertical advection"
        },
        {
            "measurements": [
                0.0117071,
                0.0117065,
                0.011712,
                0.0116956,
                0.0116981,
                0.0116964,
                0.0116967,
                0.011702,
                0.0117123,
                0.0116984
            ],
            "stencil": "advection pd bott"
        }
    ],
    "version": 0.4
}