{
    "datetime": "2019-05-29T14:18:32.159000+0000",
    "domain": [
        128,
        128,
        80
    ],
    "runinfo": {
        "backend": "mc",
        "clustername": "tave",
        "compiler": "/opt/intel/compilers_and_libraries_2018.2.199/linux/bin/intel64/icpc 18.0.2.20180210",
        "datetime": "2019-05-29T11:29:34.000000+0000",
        "grid": "structured",
        "hostname": "tave101",
        "name": "gridtools",
        "precision": "float",
        "version": "14d725a9bc015432c79e9de14ee0a2b8204198dd"
    },
    "times": [
        {
            "measurements": [
                0.00122833,
                0.00126076,
                0.00131178,
                0.00123811,
                0.00126505,
                0.00125623,
                0.0013473,
                0.00125217,
                0.00128341,
                0.00136781
            ],
            "stencil": "copy"
        },
        {
            "measurements": [
                0.0539653,
                0.0539727,
                0.0537856,
                0.053952,
                0.0534604,
                0.0538671,
                0.0536799,
                0.054029,
                0.0536749,
                0.0538945
            ],
            "stencil": "horizontal diffusion"
        },
        {
            "measurements": [
                0.162191,
                0.162458,
                0.162988,
                0.163393,
                0.163517,
                0.162602,
                0.162118,
                0.162598,
                0.161888,
                0.162827
            ],
            "stencil": "horizontal diffusion fused"
        },
        {
            "measurements": [
                0.0545039,
                0.0548022,
                0.0541406,
                0.0547974,
                0.0550001,
                0.0549016,
                0.0543242,
                0.0541384,
                0.0548074,
                0.0542176
            ],
            "stencil": "simple horizontal diffusion"
        },
        {
            "measurements": [
                0.0678596,
                0.0666089,
                0.0675092,
                0.0656655,
                0.0670099,
                0.066797,
                0.0676525,
                0.0662801,
                0.0675278,
                0.0678267
            ],
            "stencil": "vertical advection"
        },
        {
            "measurements": [
                0.0148714,
                0.0150502,
                0.0144734,
                0.0144746,
                0.0153897,
                0.0145433,
                0.014642,
                0.0146172,
                0.0146987,
                0.0142961
            ],
            "stencil": "advection pd bott"
        },
        {
            "measurements": [
                0.0196741,
                0.0190554,
                0.0192251,
                0.0193591,
                0.0193439,
                0.0193524,
                0.0197103,
                0.0196159,
                0.0190871,
                0.0191343
            ],
            "stencil": "layout transformation"
        },
        {
            "measurements": [
                0.00660491,
                0.0069046,
                0.00666904,
                0.0066812,
                0.00669599,
                0.00671244,
                0.00685716,
                0.00676751,
                0.00677037,
                0.00673389
            ],
            "stencil": "boundary conditions"
        }
    ],
    "version": 0.5
}