{
    "datetime": "2019-05-24T06:53:12.227253+0000",
    "domain": [
        256,
        256,
        80
    ],
    "runinfo": {
        "backend": "cuda",
        "clustername": "daint",
        "compiler": "/opt/nvidia/cudatoolkit9.2/9.2.148_3.19-6.0.7.1_2.1__g3d9acc8/bin/nvcc 9.2.148 (/users/vogtha/clang-3.8.1/bin/clang++ 3.8.1)",
        "datetime": "2019-05-24T06:22:30.000000+0000",
        "grid": "structured",
        "hostname": "daint102",
        "name": "gridtools",
        "precision": "double",
        "version": "d6ac209767a4f5cf2bf7eb69593c4ecea10060b4"
    },
    "times": [
        {
            "measurements": [
                0.00169053,
                0.00169149,
                0.00168896,
                0.00168506,
                0.001688,
                0.00168589,
                0.0016895,
                0.00168954,
                0.00168771,
                0.00168867
            ],
            "stencil": "copy"
        },
        {
            "measurements": [
                0.0044343,
                0.00442653,
                0.00443581,
                0.00442214,
                0.00441306,
                0.0044271,
                0.00442442,
                0.00442845,
                0.00443843,
                0.00443472
            ],
            "stencil": "horizontal diffusion"
        },
        {
            "measurements": [
                0.00398797,
                0.00398502,
                0.00400144,
                0.00398288,
                0.00397805,
                0.00397968,
                0.00398918,
                0.00398826,
                0.00398848,
                0.0039831
            ],
            "stencil": "horizontal diffusion fused"
        },
        {
            "measurements": [
                0.00460246,
                0.00456867,
                0.00458163,
                0.00457933,
                0.00457859,
                0.0045657,
                0.00457018,
                0.004576,
                0.00458326,
                0.00457098
            ],
            "stencil": "simple horizontal diffusion"
        },
        {
            "measurements": [
                0.00916547,
                0.0091633,
                0.00916733,
                0.00916762,
                0.00916208,
                0.00916806,
                0.00916755,
                0.00917056,
                0.0091641,
                0.00917635
            ],
            "stencil": "vertical advection"
        },
        {
            "measurements": [
                0.0221089,
                0.0221359,
                0.0221121,
                0.0221212,
                0.0221074,
                0.0221525,
                0.0221256,
                0.0221307,
                0.0221301,
                0.022152
            ],
            "stencil": "advection pd bott"
        },
        {
            "measurements": [
                0.00234464,
                0.00234458,
                0.0023417,
                0.00234602,
                0.00235254,
                0.00235082,
                0.00234592,
                0.00235107,
                0.00234694,
                0.00234544
            ],
            "stencil": "layout transformation"
        }
    ],
    "version": 0.5
}