{
    "config": {
        "clustername": "daint",
        "configname": "daint_gcc",
        "hostname": "daint104"
    },
    "datetime": "2018-04-23T13:14:14.298159+0000",
    "domain": [
        128,
        128,
        80
    ],
    "runtime": {
        "backend": "cuda",
        "compiler": "/opt/nvidia/cudatoolkit8.0/8.0.61_2.4.3-6.0.4.0_3.1__gb475d12/bin/nvcc",
        "datetime": "2018-04-23T12:51:10.000000+0000",
        "grid": "structured",
        "name": "gridtools",
        "precision": "double",
        "version": "6d48f343847028b8ddfad26ac0dff89aa93c6d3e"
    },
    "times": [
        {
            "measurements": [
                0.000699168,
                0.000703392,
                0.000706272,
                0.000718048,
                0.000706304,
                0.000710464,
                0.000705376,
                0.0007024,
                0.00070672,
                0.000706112
            ],
            "stencil": "copy"
        },
        {
            "measurements": [
                0.00242317,
                0.00242557,
                0.00243245,
                0.00241549,
                0.00240707,
                0.00243203,
                0.00243056,
                0.00241888,
                0.00241446,
                0.00242506
            ],
            "stencil": "horizontal diffusion"
        },
        {
            "measurements": [
                0.00217293,
                0.0021575,
                0.0021704,
                0.00217117,
                0.00218237,
                0.00215568,
                0.00215194,
                0.00215562,
                0.00215062,
                0.00215779
            ],
            "stencil": "horizontal diffusion fused"
        },
        {
            "measurements": [
                0.00189334,
                0.00189744,
                0.00188803,
                0.00189616,
                0.00189296,
                0.00190467,
                0.00189421,
                0.00190282,
                0.00190429,
                0.0019009
            ],
            "stencil": "simple horizontal diffusion"
        },
        {
            "measurements": [
                0.00271062,
                0.00270518,
                0.00270752,
                0.00270406,
                0.00271261,
                0.00272234,
                0.00271274,
                0.00271222,
                0.00271098,
                0.00271136
            ],
            "stencil": "vertical advection"
        },
        {
            "measurements": [
                0.00833907,
                0.00836682,
                0.00836669,
                0.00833475,
                0.00831722,
                0.00832394,
                0.0083145,
                0.00832112,
                0.00833181,
                0.00831421
            ],
            "stencil": "advection pd bott"
        }
    ],
    "version": 0.4
}